{
  "project_info": {
    "project_number": "297029956281",
    "firebase_url": "https://whatsapp-d293c.firebaseio.com",
    "project_id": "whatsapp-d293c",
    "storage_bucket": "whatsapp-d293c.appspot.com"
  },
  "client": [
    {
      "client_info": {
        "mobilesdk_app_id": "1:297029956281:android:f18deb2a3a64c664d12168",
        "android_client_info": {
          "package_name": "com.example.whatsapp"
        }
      },
      "oauth_client": [
        {
          "client_id": "297029956281-cohk4fe4j8l0jut7vtheup7l2rbbm2mi.apps.googleusercontent.com",
          "client_type": 3
        }
      ],
      "api_key": [
        {
          "current_key": "AIzaSyCc9SG8xkNn6wL0B-i4-NIkF8RfoIpuRus"
        }
      ],
      "services": {
        "appinvite_service": {
          "other_platform_oauth_client": [
            {
              "client_id": "297029956281-cohk4fe4j8l0jut7vtheup7l2rbbm2mi.apps.googleusercontent.com",
              "client_type": 3
            }
          ]
        }
      }
    }
  ],
  "configuration_version": "1"
}